orchestration/__init__.py
orchestration/orch_run.py
orchestration/plugin.py
orchestration/reporter.py
pytest_orchestration-0.0.10.dist-info/LICENSE
pytest_orchestration-0.0.10.dist-info/METADATA
pytest_orchestration-0.0.10.dist-info/WHEEL
pytest_orchestration-0.0.10.dist-info/entry_points.txt
pytest_orchestration-0.0.10.dist-info/top_level.txt
pytest_orchestration-0.0.10.dist-info/RECORD
