Metadata-Version: 2.1
Name: pytest-orchestration
Version: 0.0.10
Summary: A pytest plugin for orchestrating tests
Home-page: https://github.com/simlind/pytest-orchestration
Author: Simon Lindberg
Author-email: lindberg.simon@gmail.com
License: UNKNOWN
Platform: UNKNOWN
Classifier: Programming Language :: Python :: 3
Classifier: License :: OSI Approved :: MIT License
Classifier: Operating System :: OS Independent
Classifier: Framework :: Pytest
